atelier_generator/__init__.py
atelier_generator/api.py
atelier_generator/data.py
atelier_generator/webui.py
atelier_generator/templates/index.py
atelier_generator-25.3.4.dist-info/licenses/LICENSE
atelier_generator-25.3.4.dist-info/METADATA
atelier_generator-25.3.4.dist-info/WHEEL
atelier_generator-25.3.4.dist-info/top_level.txt
atelier_generator-25.3.4.dist-info/RECORD
