Metadata-Version: 2.4
Name: atelier-generator
Version: 25.3.4
Summary: A comprehensive toolkit for state-of-the-art AI image generation compatible with all devices.
Author-email: ikmalsaid <ikmalsaid@gmail.com>
Project-URL: Homepage, https://github.com/ikmalsaid/atelier-generator
Project-URL: Issues, https://github.com/ikmalsaid/atelier-generator/issues
Keywords: atelier-generator,atelier_generator
Classifier: Programming Language :: Python :: 3
Classifier: Topic :: Scientific/Engineering :: Artificial Intelligence
Classifier: License :: OSI Approved :: GNU Affero General Public License v3
Classifier: Operating System :: OS Independent
Requires-Python: >=3.8
License-File: LICENSE
Requires-Dist: colorpaws
Requires-Dist: gradio==4.38.1
Requires-Dist: fastapi==0.112.4
Requires-Dist: pydantic==2.10.6
Requires-Dist: gradio-modal
Requires-Dist: flask
Dynamic: license-file
